{
    "//": "mapping used for details page",
    "details_mapping": [
            {"name" : "pam_2015_EU_ETS_kt_CO2", "field" : "2015_EU_ETS_kt_CO2", "title" : "2015 EU ETS (kt CO2-equivalent per year)"},
            {"name" : "pam_2015_non_ETS_kt_CO2", "field" : "2015_non_ETS_kt_CO2", "title" : "2015 non-ETS (kt CO2-equivalent per year)"},
            {"name" : "pam_2015_total_kt_CO2_equivalent_per_year", "field" : "2015_total_kt_CO2_equivalent_per_year", "title" : "2015 total (kt CO2-equivalent per year)"},
            {"name" : "pam_2020_EU_ETS_kt_CO2", "field" : "2020_EU_ETS_kt_CO2", "title" : "2020 EU ETS (kt CO2-equivalent per year)"},
            {"name" : "pam_2020_non_ETS_kt_CO2", "field" : "2020_non_ETS_kt_CO2", "title" : "2020 non-ETS (kt CO2-equivalent per year)"},
            {"name" : "pam_2020_total_kt_CO2", "field" : "2020_total_kt_CO2", "title" : "2020 total (kt CO2-equivalent per year)"},
            {"name" : "pam_2025_total_kt_CO2", "field" : "2025_total_kt_CO2", "title" : "2025 total (kt CO2-equivalent per year)"},
            {"name" : "pam_2030_total_kt_CO2", "field" : "2030_total_kt_CO2", "title" : "2030 total (kt CO2-equivalent per year)"},
            {"name" : "Absolute_costs_per_year_in_million_EUR", "field" : "Absolute_costs_per_year_in_million_EUR", "title" : "Absolute costs per year in million EUR"},
            {"name" : "Additional_comment", "field" : "Additional_comment", "title" : "Additional comment"},
            {"name" : "Affected_GHG", "field" : "Affected_GHG", "title" : "Affected GHG"},
            {"name" : "Average_emission_reduction_kt_CO2", "field" : "Average_emission_reduction_kt_CO2", "title" : "Average emission reduction"},
            {"name" : "Basis_for_estimate", "field" : "Basis_for_estimate", "title" : "Basis for estimate"},
            {"name" : "Check_of_mandatory_reporting", "field" : "Check_of_mandatory_reporting", "title" : ""},
            {"name" : "Comment_on_implementation_period", "field" : "Comment_on_implementation_period", "title" : "Comment on implementation period start year"},
            {"name" : "Comments_by_MS", "field" : "Comments_by_MS", "title" : ""},
            {"name" : "Costs_in_EUR_per_tonne_CO2_equivalent_reduced_sequestered", "field" : "Costs_in_EUR_per_tonne_CO2_equivalent_reduced_sequestered", "title" : "Costs in EUR per tonne CO2 equivalent reduced/ sequestered"},
            {"name" : "Country", "field" : "Country", "title" : "Country"},
            {"name" : "CountryCode", "field" : "CountryCode", "title" : ""},
            {"name" : "Description", "field" : "Description", "title" : "Description"},
            {"name" : "Description___basis_for_cost_estimate", "field" : "Description___basis_for_cost_estimate", "title" : "Description - basis for cost estimate"},
            {"name" : "Details_on_policy_interactions", "field" : "Details_on_policy_interactions", "title" : "Details on policy interactions"},
            {"name" : "Documentation___source_of_cost_estimate", "field" : "Documentation___source_of_cost_estimate", "title" : "Documentation - source of cost estimation"},
            {"name" : "End_year", "field" : "End_year", "title" : "End year"},
            {"name" : "Factors_affected_by_PAM", "field" : "Factors_affected_by_PAM", "title" : "Factors affected by PAM"},
            {"name" : "Impact_included_in_another_policy_or_policy_package", "field" : "Impact_included_in_another_policy_or_policy_package", "title" : "Impact included in another policy or policy package?"},
            {"name" : "Inclusion_of_estimate_in_projections", "field" : "Inclusion_of_estimate_in_projections", "title" : "Inclusion of estimate in projections"},
            {"name" : "Inclusion_of_savings_related_to_EU_policies", "field" : "Inclusion_of_savings_related_to_EU_policies", "title" : "Inclusion of savings from EU policies into estimate"},
            {"name" : "Indicators_to_monitor_and_evaluate_implementation", "field" : "Indicators_to_monitor_and_evaluate_implementation", "title" : "Indicator(s) to monitor and evaluate implementation"},
            {"name" : "Interaction_with_other_policies_and_measures_at_the_national_or_EU_level", "field" : "Interaction_with_other_policies_and_measures_at_the_national_or_EU_level", "title" : "Interaction with other policies and measures at the national or EU level"},
            {"name" : "Link_to_EU_Emissions_Trading_Scheme_ETS", "field" : "Link_to_EU_Emissions_Trading_Scheme_ETS", "title" : "Link to EU Emissions Trading Scheme (ETS)"},
            {"name" : "Name", "field" : "Name", "title" : "Name"},
            {"name" : "Name_of_implementing_entities", "field" : "Name_of_implementing_entities", "title" : "Name of implementing entities"},
            {"name" : "Name_or_organisation_providing_information_on_policy", "field" : "Name_or_organisation_providing_information_on_policy", "title" : "Name or organisation providing information on policy"},
            {"name" : "Non_GHG_mitigation_benefits", "field" : "Non_GHG_mitigation_benefits", "title" : "Non GHG-mitigation benefits"},
            {"name" : "Objective", "field" : "Objective", "title" : "Objective"},
            {"name" : "Other_policy_or_policy_package_in_which_the_impact_is_included", "field" : "Other_policy_or_policy_package_in_which_the_impact_is_included", "title" : "Other policy or /policy package in which the impact is included"},
            {"name" : "PAMID", "field" : "PAMID", "title" : ""},
            {"name" : "PAM_No", "field" : "PAM_No", "title" : ""},
            {"name" : "Primary_EU_policy_responsible_objectives", "field" : "Primary_EU_policy_responsible_objectives", "title" : ""},
            {"name" : "Projection_scenario_in_which_the_PAM_is_included", "field" : "Projection_scenario_in_which_the_PAM_is_included", "title" : "Projection scenario in which the PAM is included"},
            {"name" : "Reference_source_of_estimation", "field" : "Reference_source_of_estimation", "title" : "Reference / source for estimation of emission savings"},
            {"name" : "Related_EU_policies", "field" : "Related_EU_policies", "title" : "Related EU policies"},
            {"name" : "Secondary_EU_policy_responsible_objectives", "field" : "Secondary_EU_policy_responsible_objectives", "title" : ""},
            {"name" : "Start_year", "field" : "Start_year", "title" : "Start year"},
            {"name" : "Status", "field" : "Status", "title" : "Status"},
            {"name" : "Targeted_sectors", "field" : "Targeted_sectors", "title" : "Targeted sector(s)"},
            {"name" : "Tertiary_EU_policy_responsible_objectives", "field" : "Tertiary_EU_policy_responsible_objectives", "title" : ""},
            {"name" : "Type_of_implementing_entities", "field" : "Type_of_implementing_entities", "title" : "Type of implementing entities"},
            {"name" : "Type_of_instrument", "field" : "Type_of_instrument", "title" : "Type of instrument"},
            {"name" : "Years_for_which_the_reduction_applies", "field" : "Years_for_which_the_reduction_applies", "title" : "Year(s) for which the reduction applies"}
        ],

    "//": "mapping used for csv/tsv download",
    "download_mapping":{

        "//": "if true include all fields from elastic",
        "use_all_fields": true,

        "//": "if true use the mapping from the detail_mapping, if use_all_fields is false, only these fields will be used in the download",
        "//": "title is used if it exists in the mapping, otherwise name is used",
        "use_mapping_from_details_mapping":true,

        "//": "download specific mapping, it should look similar as the details_mapping, name is not required, only field and title are used",
        "mapping":[],

        "//": "order of fields from es in the export, if specified, use_all_fields is ignored and only these fields will be used in the download",
        "order": []
    }
}